ansys/dpf/composites/__init__.py
ansys/dpf/composites/_composite_model_factory.py
ansys/dpf/composites/_composite_model_impl.py
ansys/dpf/composites/_composite_model_impl_2023r2.py
ansys/dpf/composites/_composite_model_impl_helpers.py
ansys/dpf/composites/_indexer.py
ansys/dpf/composites/_sampling_point_helpers.py
ansys/dpf/composites/_typing_helper.py
ansys/dpf/composites/composite_model.py
ansys/dpf/composites/composite_scope.py
ansys/dpf/composites/constants.py
ansys/dpf/composites/data_sources.py
ansys/dpf/composites/example_helper/__init__.py
ansys/dpf/composites/failure_criteria/__init__.py
ansys/dpf/composites/failure_criteria/_combined_failure_criterion.py
ansys/dpf/composites/failure_criteria/_core_failure.py
ansys/dpf/composites/failure_criteria/_cuntze.py
ansys/dpf/composites/failure_criteria/_face_sheet_wrinkling.py
ansys/dpf/composites/failure_criteria/_failure_criterion_base.py
ansys/dpf/composites/failure_criteria/_failure_mode_enum.py
ansys/dpf/composites/failure_criteria/_hashin.py
ansys/dpf/composites/failure_criteria/_hoffman.py
ansys/dpf/composites/failure_criteria/_larc.py
ansys/dpf/composites/failure_criteria/_max_strain.py
ansys/dpf/composites/failure_criteria/_max_stress.py
ansys/dpf/composites/failure_criteria/_puck.py
ansys/dpf/composites/failure_criteria/_quadratic_failure_criterion.py
ansys/dpf/composites/failure_criteria/_shear_crimping.py
ansys/dpf/composites/failure_criteria/_tsai_hill.py
ansys/dpf/composites/failure_criteria/_tsai_wu.py
ansys/dpf/composites/failure_criteria/_von_mises.py
ansys/dpf/composites/layup_info/__init__.py
ansys/dpf/composites/layup_info/_add_layup_info_to_mesh.py
ansys/dpf/composites/layup_info/_element_info.py
ansys/dpf/composites/layup_info/_enums.py
ansys/dpf/composites/layup_info/_layup_info.py
ansys/dpf/composites/layup_info/_reference_surface.py
ansys/dpf/composites/layup_info/_solid_stack_info.py
ansys/dpf/composites/layup_info/material_operators.py
ansys_dpf_composites-0.7.0.dist-info/AUTHORS
ansys_dpf_composites-0.7.0.dist-info/LICENSE
ansys_dpf_composites-0.7.0.dist-info/METADATA
ansys_dpf_composites-0.7.0.dist-info/WHEEL
ansys_dpf_composites-0.7.0.dist-info/RECORD
