Metadata-Version: 2.3
Name: ansys-dpf-composites
Version: 0.7.0
Summary: Post-processing of composite structures based on Ansys DPF
License: MIT
Author: ANSYS, Inc.
Author-email: ansys.support@ansys.com
Maintainer: PyAnsys developers
Maintainer-email: pyansys.maintainers@ansys.com
Requires-Python: >=3.10,<4
Classifier: Development Status :: 5 - Production/Stable
Classifier: License :: OSI Approved :: MIT License
Classifier: Operating System :: OS Independent
Classifier: Programming Language :: Python :: 3
Classifier: Programming Language :: Python :: 3.10
Classifier: Programming Language :: Python :: 3.11
Classifier: Programming Language :: Python :: 3.12
Classifier: Programming Language :: Python :: 3.13
Provides-Extra: all
Provides-Extra: build
Provides-Extra: docs
Provides-Extra: examples
Provides-Extra: pre-commit
Provides-Extra: test
Requires-Dist: Sphinx (>=5.0.1) ; extra == "all" or extra == "docs"
Requires-Dist: ansys-dpf-core (>=0.10.1)
Requires-Dist: ansys-sphinx-theme (>=0) ; extra == "all" or extra == "docs"
Requires-Dist: build (>=0.8.0) ; extra == "all" or extra == "build"
Requires-Dist: fatpack (>=0.5) ; extra == "all" or extra == "docs" or extra == "examples"
Requires-Dist: matplotlib (>=3.8.0)
Requires-Dist: mypy (>=1.2.0) ; extra == "all" or extra == "pre-commit"
Requires-Dist: mypy-extensions (>=1.0.0) ; extra == "all" or extra == "pre-commit"
Requires-Dist: numpy (>=1.25)
Requires-Dist: numpydoc (>=1.5) ; extra == "all" or extra == "docs"
Requires-Dist: packaging
Requires-Dist: pre-commit ; extra == "all" or extra == "pre-commit"
Requires-Dist: pylint (>=2.13) ; extra == "all" or extra == "pre-commit"
Requires-Dist: pypandoc (>=1.8.1) ; extra == "all" or extra == "docs"
Requires-Dist: pytest (>=7.1.2) ; extra == "all" or extra == "test"
Requires-Dist: pytest-cov (>=3.0.0) ; extra == "all" or extra == "test"
Requires-Dist: pytest-rerunfailures (>=11.1.2) ; extra == "all" or extra == "test"
Requires-Dist: pyvista[jupyter,trame] (>=0.40.2,!=0.44.2) ; extra == "all" or extra == "docs" or extra == "examples"
Requires-Dist: scipy (>=1.9.0) ; extra == "all" or extra == "docs" or extra == "examples"
Requires-Dist: sphinx-autodoc-typehints (>=1.19,<1.20.2) ; extra == "all" or extra == "docs"
Requires-Dist: sphinx-copybutton (>=0.4) ; extra == "all" or extra == "docs"
Requires-Dist: sphinx-design (>=0.3.0) ; extra == "all" or extra == "docs"
Requires-Dist: sphinx_gallery (>=0.11.0) ; extra == "all" or extra == "docs"
Requires-Dist: twine (>=4.0.1) ; extra == "all" or extra == "build"
Project-URL: Documentation, https://composites.dpf.docs.pyansys.com
Project-URL: Repository, https://github.com/ansys/pydpf-composites
